{
    "district": {
        "S\u00e2les": "Gruy\u00e8re",
        "Estavayer-le-Lac": "Broye",
        "Vuadens": "Gruy\u00e8re",
        "Romont": "Gl\u00e2ne",
        "Marsens": "Gruy\u00e8re",
        "Billens": "Gl\u00e2ne",
        "Flamatt": "Singine",
        "Bulle": "Gruy\u00e8re",
        "Fribourg": "Sarine",
        "Cottens": "Sarine",
        "Broc": "Gruy\u00e8re",
        "Plaffeien": "Singine",
        "Tafers": "Singine",
        "Montagny-la-Ville": "Broye",
        "Jeuss": "Singine",
        "Morlon": "Gruy\u00e8re",
        "Domdidier": "Broye",
        "Marly": "Sarine",
        "Givisiez": "Sarine",
        "Charmey": "Gruy\u00e8re",
        "Giffers": "Singine",
        "Ch\u00e2tel-St-Denis": "Veveyse",
        "B\u00f6singen": "Singine",
        "Sorens": "Gruy\u00e8re",
        "Gruy\u00e8res": "Gruy\u00e8re",
        "Villars-sur-Gl\u00e2ne": "Sarine",
        "Vuists./Romont": "Gl\u00e2ne",
        "La Roche": "Gruy\u00e8re",
        "Courtepin": "Lac",
        "Murten": "Lac",
        "Villars-sous-Mont": "Gruy\u00e8re",
        "Le Mouret": "Sarine",
        "Farvagny-le-Grand": "Sarine",
        "Gletterens": "Broye",
        "Ulmiz": "Singine",
        "Attalens": "Veveyse",
        "Siviriez": "Gl\u00e2ne",
        "Ursy": "Gl\u00e2ne",
        "Sugiez": "Lac",
        "Kerzers": "Lac",
        "D\u00fcdingen": "Singine",
        "Schmitten": "Singine",
        "Vuisternens-dt-Romont": "Gl\u00e2ne",
        "Heitenried": "Singine",
        "Gurmels": "Lac"
    }
}